<?xml version="1.0" encoding="windows-1252"?>
<monthlyevents>
	<event>
		<title>Commodity Prices y/y</title>
		<currency>AUD</currency>
		<date>01-02-2023</date>
		<time>12:30am</time>
		<forecast></forecast>
		<previous>14.1%</previous>
		<impact>Low</impact>
	</event>
	<event>
		<title>Nationwide HPI m/m</title>
		<currency>GBP</currency>
		<date>01-02-2023</date>
		<time>2:00am</time>
		<forecast>-0.5%</forecast>
		<previous>-0.3%</previous>
		<impact>Low</impact>
	</event>
	<event>
		<title>Spanish Manufacturing PMI</title>
		<currency>EUR</currency>
		<date>01-02-2023</date>
		<time>3:15am</time>
		<forecast>47.9</forecast>
		<previous>46.4</previous>
		<impact>Low</impact>
	</event>
	<event>
		<title>Manufacturing PMI</title>
		<currency>CHF</currency>
		<date>01-02-2023</date>
		<time>3:30am</time>
		<forecast>54.3</forecast>
		<previous>54.1</previous>
		<impact>Low</impact>
	</event>
	<event>
		<title>Italian Manufacturing PMI</title>
		<currency>EUR</currency>
		<date>01-02-2023</date>
		<time>3:45am</time>
		<forecast>49.6</forecast>
		<previous>48.5</previous>
		<impact>Low</impact>
	</event>
	<event>
		<title>French Final Manufacturing PMI</title>
		<currency>EUR</currency>
		<date>01-02-2023</date>
		<time>3:50am</time>
		<forecast>50.8</forecast>
		<previous>50.8</previous>
		<impact>Low</impact>
	</event>
	<event>
		<title>German Final Manufacturing PMI</title>
		<currency>EUR</currency>
		<date>01-02-2023</date>
		<time>3:55am</time>
		<forecast>47.0</forecast>
		<previous>47.0</previous>
		<impact>Low</impact>
	</event>
	<event>
		<title>Final Manufacturing PMI</title>
		<currency>EUR</currency>
		<date>01-02-2023</date>
		<time>4:00am</time>
		<forecast>48.8</forecast>
		<previous>48.8</previous>
		<impact>Low</impact>
	</event>
	<event>
		<title>Final Manufacturing PMI</title>
		<currency>GBP</currency>
		<date>01-02-2023</date>
		<time>4:30am</time>
		<forecast>46.7</forecast>
		<previous>46.7</previous>
		<impact>Low</impact>
	</event>
	<event>
		<title>CPI Flash Estimate y/y</title>
		<currency>EUR</currency>
		<date>01-02-2023</date>
		<time>5:00am</time>
		<forecast>9.0%</forecast>
		<previous>9.2%</previous>
		<impact>Medium</impact>
	</event>
	<event>
		<title>Core CPI Flash Estimate y/y</title>
		<currency>EUR</currency>
		<date>01-02-2023</date>
		<time>5:00am</time>
		<forecast>5.1%</forecast>
		<previous>5.2%</previous>
		<impact>Medium</impact>
	</event>
	<event>
		<title>Italian Prelim CPI m/m</title>
		<currency>EUR</currency>
		<date>01-02-2023</date>
		<time>5:00am</time>
		<forecast>0.0%</forecast>
		<previous>0.3%</previous>
		<impact>Low</impact>
	</event>
	<event>
		<title>Unemployment Rate</title>
		<currency>EUR</currency>
		<date>01-02-2023</date>
		<time>5:00am</time>
		<forecast>6.5%</forecast>
		<previous>6.6%</previous>
		<impact>Low</impact>
	</event>
	<event>
		<title>OPEC-JMMC Meetings</title>
		<currency>All</currency>
		<date>01-02-2023</date>
		<time>All Day</time>
		<forecast></forecast>
		<previous></previous>
		<impact>Medium</impact>
	</event>
	<event>
		<title>German 10-y Bond Auction</title>
		<currency>EUR</currency>
		<date>01-02-2023</date>
		<time>5:34am</time>
		<forecast></forecast>
		<previous>2.25|1.4</previous>
		<impact>Low</impact>
	</event>
	<event>
		<title>ADP Non-Farm Employment Change</title>
		<currency>USD</currency>
		<date>01-02-2023</date>
		<time>8:15am</time>
		<forecast>176K</forecast>
		<previous>253K</previous>
		<impact>High</impact>
	</event>
	<event>
		<title>Manufacturing PMI</title>
		<currency>CAD</currency>
		<date>01-02-2023</date>
		<time>9:30am</time>
		<forecast></forecast>
		<previous>49.2</previous>
		<impact>Low</impact>
	</event>
	<event>
		<title>Final Manufacturing PMI</title>
		<currency>USD</currency>
		<date>01-02-2023</date>
		<time>9:45am</time>
		<forecast>46.8</forecast>
		<previous>46.8</previous>
		<impact>Low</impact>
	</event>
	<event>
		<title>ISM Manufacturing PMI</title>
		<currency>USD</currency>
		<date>01-02-2023</date>
		<time>10:00am</time>
		<forecast>48.0</forecast>
		<previous>48.4</previous>
		<impact>High</impact>
	</event>
	<event>
		<title>JOLTS Job Openings</title>
		<currency>USD</currency>
		<date>01-02-2023</date>
		<time>10:00am</time>
		<forecast>10.28M</forecast>
		<previous>10.44M</previous>
		<impact>High</impact>
	</event>
	<event>
		<title>Construction Spending m/m</title>
		<currency>USD</currency>
		<date>01-02-2023</date>
		<time>10:00am</time>
		<forecast>0.0%</forecast>
		<previous>0.5%</previous>
		<impact>Low</impact>
	</event>
	<event>
		<title>ISM Manufacturing Prices</title>
		<currency>USD</currency>
		<date>01-02-2023</date>
		<time>10:00am</time>
		<forecast>40.6</forecast>
		<previous>39.4</previous>
		<impact>Low</impact>
	</event>
	<event>
		<title>Wards Total Vehicle Sales</title>
		<currency>USD</currency>
		<date>01-02-2023</date>
		<time>All Day</time>
		<forecast>15.2M</forecast>
		<previous>13.3M</previous>
		<impact>Low</impact>
	</event>
	<event>
		<title>Crude Oil Inventories</title>
		<currency>USD</currency>
		<date>01-02-2023</date>
		<time>10:30am</time>
		<forecast>-1.0M</forecast>
		<previous>0.5M</previous>
		<impact>Low</impact>
	</event>
	<event>
		<title>FOMC Statement</title>
		<currency>USD</currency>
		<date>01-02-2023</date>
		<time>2:00pm</time>
		<forecast></forecast>
		<previous></previous>
		<impact>High</impact>
	</event>
	<event>
		<title>Federal Funds Rate</title>
		<currency>USD</currency>
		<date>01-02-2023</date>
		<time>2:00pm</time>
		<forecast>4.75%</forecast>
		<previous>4.50%</previous>
		<impact>High</impact>
	</event>
	<event>
		<title>FOMC Press Conference</title>
		<currency>USD</currency>
		<date>01-02-2023</date>
		<time>2:30pm</time>
		<forecast></forecast>
		<previous></previous>
		<impact>High</impact>
	</event>
	<event>
		<title>Building Consents m/m</title>
		<currency>NZD</currency>
		<date>01-02-2023</date>
		<time>4:45pm</time>
		<forecast></forecast>
		<previous>6.7%</previous>
		<impact>Low</impact>
	</event>
	<event>
		<title>Monetary Base y/y</title>
		<currency>JPY</currency>
		<date>01-02-2023</date>
		<time>6:50pm</time>
		<forecast>-3.2%</forecast>
		<previous>-6.1%</previous>
		<impact>Low</impact>
	</event>
	<event>
		<title>Building Approvals m/m</title>
		<currency>AUD</currency>
		<date>01-02-2023</date>
		<time>7:30pm</time>
		<forecast>1.1%</forecast>
		<previous>-8.8%</previous>
		<impact>Low</impact>
	</event>
	<event>
		<title>NAB Quarterly Business Confidence</title>
		<currency>AUD</currency>
		<date>01-02-2023</date>
		<time>7:30pm</time>
		<forecast></forecast>
		<previous>9</previous>
		<impact>Low</impact>
	</event>
	<event>
		<title>10-y Bond Auction</title>
		<currency>JPY</currency>
		<date>01-02-2023</date>
		<time>10:35pm</time>
		<forecast></forecast>
		<previous>0.50|4.8</previous>
		<impact>Low</impact>
	</event>
	<event>
		<title>German Trade Balance</title>
		<currency>EUR</currency>
		<date>02-02-2023</date>
		<time>2:00am</time>
		<forecast>9.2B</forecast>
		<previous>10.9B</previous>
		<impact>Low</impact>
	</event>
	<event>
		<title>SECO Consumer Climate</title>
		<currency>CHF</currency>
		<date>02-02-2023</date>
		<time>3:00am</time>
		<forecast>-38</forecast>
		<previous>-47</previous>
		<impact>Low</impact>
	</event>
	<event>
		<title>Spanish Unemployment Change</title>
		<currency>EUR</currency>
		<date>02-02-2023</date>
		<time>3:00am</time>
		<forecast>-15.2K</forecast>
		<previous>-43.7K</previous>
		<impact>Low</impact>
	</event>
	<event>
		<title>French 10-y Bond Auction</title>
		<currency>EUR</currency>
		<date>02-02-2023</date>
		<time>4:59am</time>
		<forecast></forecast>
		<previous>2.77|1.9</previous>
		<impact>Low</impact>
	</event>
	<event>
		<title>BOE Monetary Policy Report</title>
		<currency>GBP</currency>
		<date>02-02-2023</date>
		<time>7:00am</time>
		<forecast></forecast>
		<previous></previous>
		<impact>High</impact>
	</event>
	<event>
		<title>MPC Official Bank Rate Votes</title>
		<currency>GBP</currency>
		<date>02-02-2023</date>
		<time>7:00am</time>
		<forecast>7-0-2</forecast>
		<previous>7-0-2</previous>
		<impact>High</impact>
	</event>
	<event>
		<title>Monetary Policy Summary</title>
		<currency>GBP</currency>
		<date>02-02-2023</date>
		<time>7:00am</time>
		<forecast></forecast>
		<previous></previous>
		<impact>High</impact>
	</event>
	<event>
		<title>Official Bank Rate</title>
		<currency>GBP</currency>
		<date>02-02-2023</date>
		<time>7:00am</time>
		<forecast>4.00%</forecast>
		<previous>3.50%</previous>
		<impact>High</impact>
	</event>
	<event>
		<title>BOE Gov Bailey Speaks</title>
		<currency>GBP</currency>
		<date>02-02-2023</date>
		<time>7:30am</time>
		<forecast></forecast>
		<previous></previous>
		<impact>High</impact>
	</event>
	<event>
		<title>Challenger Job Cuts y/y</title>
		<currency>USD</currency>
		<date>02-02-2023</date>
		<time>7:30am</time>
		<forecast></forecast>
		<previous>129.1%</previous>
		<impact>Low</impact>
	</event>
	<event>
		<title>Main Refinancing Rate</title>
		<currency>EUR</currency>
		<date>02-02-2023</date>
		<time>8:15am</time>
		<forecast>3.00%</forecast>
		<previous>2.50%</previous>
		<impact>High</impact>
	</event>
	<event>
		<title>Monetary Policy Statement</title>
		<currency>EUR</currency>
		<date>02-02-2023</date>
		<time>8:15am</time>
		<forecast></forecast>
		<previous></previous>
		<impact>High</impact>
	</event>
	<event>
		<title>Building Permits m/m</title>
		<currency>CAD</currency>
		<date>02-02-2023</date>
		<time>8:30am</time>
		<forecast>-2.1%</forecast>
		<previous>14.9%</previous>
		<impact>Low</impact>
	</event>
	<event>
		<title>Unemployment Claims</title>
		<currency>USD</currency>
		<date>02-02-2023</date>
		<time>8:30am</time>
		<forecast>196K</forecast>
		<previous>186K</previous>
		<impact>Medium</impact>
	</event>
	<event>
		<title>Prelim Nonfarm Productivity q/q</title>
		<currency>USD</currency>
		<date>02-02-2023</date>
		<time>8:30am</time>
		<forecast>2.5%</forecast>
		<previous>0.8%</previous>
		<impact>Low</impact>
	</event>
	<event>
		<title>Prelim Unit Labor Costs q/q</title>
		<currency>USD</currency>
		<date>02-02-2023</date>
		<time>8:30am</time>
		<forecast>1.6%</forecast>
		<previous>2.4%</previous>
		<impact>Low</impact>
	</event>
	<event>
		<title>ECB Press Conference</title>
		<currency>EUR</currency>
		<date>02-02-2023</date>
		<time>8:45am</time>
		<forecast></forecast>
		<previous></previous>
		<impact>High</impact>
	</event>
	<event>
		<title>Factory Orders m/m</title>
		<currency>USD</currency>
		<date>02-02-2023</date>
		<time>10:00am</time>
		<forecast>2.3%</forecast>
		<previous>-1.9%</previous>
		<impact>Low</impact>
	</event>
	<event>
		<title>Natural Gas Storage</title>
		<currency>USD</currency>
		<date>02-02-2023</date>
		<time>10:30am</time>
		<forecast>-146B</forecast>
		<previous>-91B</previous>
		<impact>Low</impact>
	</event>
	<event>
		<title>SNB Chairman Jordan Speaks</title>
		<currency>CHF</currency>
		<date>02-02-2023</date>
		<time>12:30pm</time>
		<forecast></forecast>
		<previous></previous>
		<impact>Medium</impact>
	</event>
	<event>
		<title>Caixin Services PMI</title>
		<currency>CNY</currency>
		<date>02-02-2023</date>
		<time>8:45pm</time>
		<forecast>51.1</forecast>
		<previous>48.0</previous>
		<impact>Low</impact>
	</event>
	<event>
		<title>French Industrial Production m/m</title>
		<currency>EUR</currency>
		<date>03-02-2023</date>
		<time>2:45am</time>
		<forecast>0.2%</forecast>
		<previous>2.0%</previous>
		<impact>Low</impact>
	</event>
	<event>
		<title>Spanish Services PMI</title>
		<currency>EUR</currency>
		<date>03-02-2023</date>
		<time>3:15am</time>
		<forecast>52.5</forecast>
		<previous>51.6</previous>
		<impact>Low</impact>
	</event>
	<event>
		<title>Gov Board Member Maechler Speaks</title>
		<currency>CHF</currency>
		<date>03-02-2023</date>
		<time>3:30am</time>
		<forecast></forecast>
		<previous></previous>
		<impact>Medium</impact>
	</event>
	<event>
		<title>Italian Services PMI</title>
		<currency>EUR</currency>
		<date>03-02-2023</date>
		<time>3:45am</time>
		<forecast>50.9</forecast>
		<previous>49.9</previous>
		<impact>Low</impact>
	</event>
	<event>
		<title>French Final Services PMI</title>
		<currency>EUR</currency>
		<date>03-02-2023</date>
		<time>3:50am</time>
		<forecast>49.2</forecast>
		<previous>49.2</previous>
		<impact>Low</impact>
	</event>
	<event>
		<title>German Final Services PMI</title>
		<currency>EUR</currency>
		<date>03-02-2023</date>
		<time>3:55am</time>
		<forecast>50.4</forecast>
		<previous>50.4</previous>
		<impact>Low</impact>
	</event>
	<event>
		<title>Final Services PMI</title>
		<currency>EUR</currency>
		<date>03-02-2023</date>
		<time>4:00am</time>
		<forecast>50.7</forecast>
		<previous>50.7</previous>
		<impact>Low</impact>
	</event>
	<event>
		<title>Final Services PMI</title>
		<currency>GBP</currency>
		<date>03-02-2023</date>
		<time>4:30am</time>
		<forecast>48.0</forecast>
		<previous>48.0</previous>
		<impact>Low</impact>
	</event>
	<event>
		<title>PPI m/m</title>
		<currency>EUR</currency>
		<date>03-02-2023</date>
		<time>5:00am</time>
		<forecast>-0.6%</forecast>
		<previous>-1.0%</previous>
		<impact>Low</impact>
	</event>
	<event>
		<title>MPC Member Pill Speaks</title>
		<currency>GBP</currency>
		<date>03-02-2023</date>
		<time>7:15am</time>
		<forecast></forecast>
		<previous></previous>
		<impact>Low</impact>
	</event>
	<event>
		<title>Average Hourly Earnings m/m</title>
		<currency>USD</currency>
		<date>03-02-2023</date>
		<time>8:30am</time>
		<forecast>0.3%</forecast>
		<previous>0.4%</previous>
		<impact>High</impact>
	</event>
	<event>
		<title>Non-Farm Employment Change</title>
		<currency>USD</currency>
		<date>03-02-2023</date>
		<time>8:30am</time>
		<forecast>193K</forecast>
		<previous>260K</previous>
		<impact>High</impact>
	</event>
	<event>
		<title>Unemployment Rate</title>
		<currency>USD</currency>
		<date>03-02-2023</date>
		<time>8:30am</time>
		<forecast>3.6%</forecast>
		<previous>3.5%</previous>
		<impact>High</impact>
	</event>
	<event>
		<title>Final Services PMI</title>
		<currency>USD</currency>
		<date>03-02-2023</date>
		<time>9:45am</time>
		<forecast>46.6</forecast>
		<previous>46.6</previous>
		<impact>Low</impact>
	</event>
	<event>
		<title>ISM Services PMI</title>
		<currency>USD</currency>
		<date>03-02-2023</date>
		<time>10:00am</time>
		<forecast>50.5</forecast>
		<previous>49.6</previous>
		<impact>High</impact>
	</event>
	<event>
		<title/>
		<currency></currency>
		<date>04-02-2023</date>
		<time>10:00am</time>
		<forecast></forecast>
		<previous></previous>
		<impact></impact>
	</event>
	<event>
		<title>Bank Holiday</title>
		<currency>NZD</currency>
		<date>05-02-2023</date>
		<time>All Day</time>
		<forecast></forecast>
		<previous></previous>
		<impact>Holiday</impact>
	</event>
	<event>
		<title>MI Inflation Gauge m/m</title>
		<currency>AUD</currency>
		<date>05-02-2023</date>
		<time>7:03pm</time>
		<forecast></forecast>
		<previous>0.2%</previous>
		<impact>Low</impact>
	</event>
	<event>
		<title>Retail Sales m/m</title>
		<currency>AUD</currency>
		<date>05-02-2023</date>
		<time>7:30pm</time>
		<forecast>-3.9%</forecast>
		<previous>-3.9%</previous>
		<impact>Low</impact>
	</event>
	<event>
		<title>German Factory Orders m/m</title>
		<currency>EUR</currency>
		<date>06-02-2023</date>
		<time>2:00am</time>
		<forecast>2.1%</forecast>
		<previous>-4.4%</previous>
		<impact>Low</impact>
	</event>
	<event>
		<title>MPC Member Mann Speaks</title>
		<currency>GBP</currency>
		<date>06-02-2023</date>
		<time>3:40am</time>
		<forecast></forecast>
		<previous></previous>
		<impact>Low</impact>
	</event>
	<event>
		<title>Sentix Investor Confidence</title>
		<currency>EUR</currency>
		<date>06-02-2023</date>
		<time>4:30am</time>
		<forecast>-12.9</forecast>
		<previous>-17.5</previous>
		<impact>Low</impact>
	</event>
	<event>
		<title>Construction PMI</title>
		<currency>GBP</currency>
		<date>06-02-2023</date>
		<time>4:30am</time>
		<forecast>48.5</forecast>
		<previous>48.8</previous>
		<impact>Low</impact>
	</event>
	<event>
		<title>Retail Sales m/m</title>
		<currency>EUR</currency>
		<date>06-02-2023</date>
		<time>5:00am</time>
		<forecast>-2.4%</forecast>
		<previous>1.2%</previous>
		<impact>Low</impact>
	</event>
	<event>
		<title>Ivey PMI</title>
		<currency>CAD</currency>
		<date>06-02-2023</date>
		<time>10:00am</time>
		<forecast>42.3</forecast>
		<previous>33.4</previous>
		<impact>Medium</impact>
	</event>
	<event>
		<title>MPC Member Pill Speaks</title>
		<currency>GBP</currency>
		<date>06-02-2023</date>
		<time>12:00pm</time>
		<forecast></forecast>
		<previous></previous>
		<impact>Low</impact>
	</event>
	<event>
		<title>Loan Officer Survey</title>
		<currency>USD</currency>
		<date>06-02-2023</date>
		<time>2:00pm</time>
		<forecast></forecast>
		<previous></previous>
		<impact>Low</impact>
	</event>
	<event>
		<title>Average Cash Earnings y/y</title>
		<currency>JPY</currency>
		<date>06-02-2023</date>
		<time>6:30pm</time>
		<forecast>2.5%</forecast>
		<previous>1.9%</previous>
		<impact>Low</impact>
	</event>
	<event>
		<title>Household Spending y/y</title>
		<currency>JPY</currency>
		<date>06-02-2023</date>
		<time>6:30pm</time>
		<forecast>-0.3%</forecast>
		<previous>-1.2%</previous>
		<impact>Low</impact>
	</event>
	<event>
		<title>ANZ Commodity Prices m/m</title>
		<currency>NZD</currency>
		<date>06-02-2023</date>
		<time>7:00pm</time>
		<forecast></forecast>
		<previous>-0.2%</previous>
		<impact>Low</impact>
	</event>
	<event>
		<title>BRC Retail Sales Monitor y/y</title>
		<currency>GBP</currency>
		<date>06-02-2023</date>
		<time>7:01pm</time>
		<forecast>3.9%</forecast>
		<previous>6.5%</previous>
		<impact>Low</impact>
	</event>
	<event>
		<title>Trade Balance</title>
		<currency>AUD</currency>
		<date>06-02-2023</date>
		<time>7:30pm</time>
		<forecast>12.50B</forecast>
		<previous>13.48B</previous>
		<impact>Low</impact>
	</event>
	<event>
		<title>Cash Rate</title>
		<currency>AUD</currency>
		<date>06-02-2023</date>
		<time>10:30pm</time>
		<forecast>3.35%</forecast>
		<previous>3.10%</previous>
		<impact>High</impact>
	</event>
	<event>
		<title>RBA Rate Statement</title>
		<currency>AUD</currency>
		<date>06-02-2023</date>
		<time>10:30pm</time>
		<forecast></forecast>
		<previous></previous>
		<impact>High</impact>
	</event>
	<event>
		<title>30-y Bond Auction</title>
		<currency>JPY</currency>
		<date>06-02-2023</date>
		<time>10:35pm</time>
		<forecast></forecast>
		<previous>1.65|3.1</previous>
		<impact>Low</impact>
	</event>
	<event>
		<title>Leading Indicators</title>
		<currency>JPY</currency>
		<date>07-02-2023</date>
		<time>12:00am</time>
		<forecast>97.0%</forecast>
		<previous>97.4%</previous>
		<impact>Low</impact>
	</event>
	<event>
		<title>Unemployment Rate</title>
		<currency>CHF</currency>
		<date>07-02-2023</date>
		<time>1:45am</time>
		<forecast>1.9%</forecast>
		<previous>1.9%</previous>
		<impact>Low</impact>
	</event>
	<event>
		<title>German Industrial Production m/m</title>
		<currency>EUR</currency>
		<date>07-02-2023</date>
		<time>2:00am</time>
		<forecast>-0.7%</forecast>
		<previous>0.4%</previous>
		<impact>Low</impact>
	</event>
	<event>
		<title>Halifax HPI m/m</title>
		<currency>GBP</currency>
		<date>07-02-2023</date>
		<time>2:00am</time>
		<forecast>-0.8%</forecast>
		<previous>-1.3%</previous>
		<impact>Low</impact>
	</event>
	<event>
		<title>French Gov Budget Balance</title>
		<currency>EUR</currency>
		<date>07-02-2023</date>
		<time>2:45am</time>
		<forecast></forecast>
		<previous>-159.3B</previous>
		<impact>Low</impact>
	</event>
	<event>
		<title>French Trade Balance</title>
		<currency>EUR</currency>
		<date>07-02-2023</date>
		<time>2:45am</time>
		<forecast>-12.1B</forecast>
		<previous>-13.6B</previous>
		<impact>Low</impact>
	</event>
	<event>
		<title>Foreign Currency Reserves</title>
		<currency>CHF</currency>
		<date>07-02-2023</date>
		<time>3:00am</time>
		<forecast></forecast>
		<previous>784B</previous>
		<impact>Low</impact>
	</event>
	<event>
		<title>MPC Member Ramsden Speaks</title>
		<currency>GBP</currency>
		<date>07-02-2023</date>
		<time>4:00am</time>
		<forecast></forecast>
		<previous></previous>
		<impact>Low</impact>
	</event>
	<event>
		<title>Trade Balance</title>
		<currency>CAD</currency>
		<date>07-02-2023</date>
		<time>8:30am</time>
		<forecast>-0.6B</forecast>
		<previous>-0.2B</previous>
		<impact>Low</impact>
	</event>
	<event>
		<title>Trade Balance</title>
		<currency>USD</currency>
		<date>07-02-2023</date>
		<time>8:30am</time>
		<forecast>-68.5B</forecast>
		<previous>-61.0B</previous>
		<impact>Low</impact>
	</event>
	<event>
		<title>IBD/TIPP Economic Optimism</title>
		<currency>USD</currency>
		<date>07-02-2023</date>
		<time>10:00am</time>
		<forecast>44.3</forecast>
		<previous>42.3</previous>
		<impact>Low</impact>
	</event>
	<event>
		<title>GDT Price Index</title>
		<currency>NZD</currency>
		<date>07-02-2023</date>
		<time>10:07am</time>
		<forecast></forecast>
		<previous>-0.1%</previous>
		<impact>Low</impact>
	</event>
	<event>
		<title>MPC Member Cunliffe Speaks</title>
		<currency>GBP</currency>
		<date>07-02-2023</date>
		<time>10:30am</time>
		<forecast></forecast>
		<previous></previous>
		<impact>Low</impact>
	</event>
	<event>
		<title>BOC Gov Macklem Speaks</title>
		<currency>CAD</currency>
		<date>07-02-2023</date>
		<time>12:30pm</time>
		<forecast></forecast>
		<previous></previous>
		<impact>High</impact>
	</event>
	<event>
		<title>Fed Chair Powell Speaks</title>
		<currency>USD</currency>
		<date>07-02-2023</date>
		<time>12:40pm</time>
		<forecast></forecast>
		<previous></previous>
		<impact>High</impact>
	</event>
	<event>
		<title>FOMC Member Barr Speaks</title>
		<currency>USD</currency>
		<date>07-02-2023</date>
		<time>2:00pm</time>
		<forecast></forecast>
		<previous></previous>
		<impact>Low</impact>
	</event>
	<event>
		<title>Consumer Credit m/m</title>
		<currency>USD</currency>
		<date>07-02-2023</date>
		<time>3:00pm</time>
		<forecast>25.0B</forecast>
		<previous>33.1B</previous>
		<impact>Low</impact>
	</event>
	<event>
		<title>Bank Lending y/y</title>
		<currency>JPY</currency>
		<date>07-02-2023</date>
		<time>6:50pm</time>
		<forecast>2.5%</forecast>
		<previous>2.7%</previous>
		<impact>Low</impact>
	</event>
	<event>
		<title>Current Account</title>
		<currency>JPY</currency>
		<date>07-02-2023</date>
		<time>6:50pm</time>
		<forecast>1.25T</forecast>
		<previous>1.92T</previous>
		<impact>Low</impact>
	</event>
	<event>
		<title>President Biden Speaks</title>
		<currency>USD</currency>
		<date>07-02-2023</date>
		<time>9:00pm</time>
		<forecast></forecast>
		<previous></previous>
		<impact>Low</impact>
	</event>
	<event>
		<title>Economy Watchers Sentiment</title>
		<currency>JPY</currency>
		<date>08-02-2023</date>
		<time>12:00am</time>
		<forecast>48.3</forecast>
		<previous>47.9</previous>
		<impact>Low</impact>
	</event>
	<event>
		<title>French Prelim Private Payrolls q/q</title>
		<currency>EUR</currency>
		<date>08-02-2023</date>
		<time>2:45am</time>
		<forecast>0.3%</forecast>
		<previous>0.6%</previous>
		<impact>Low</impact>
	</event>
	<event>
		<title>Italian Retail Sales m/m</title>
		<currency>EUR</currency>
		<date>08-02-2023</date>
		<time>4:00am</time>
		<forecast>-0.8%</forecast>
		<previous>0.8%</previous>
		<impact>Low</impact>
	</event>
	<event>
		<title>FOMC Member Williams Speaks</title>
		<currency>USD</currency>
		<date>08-02-2023</date>
		<time>9:15am</time>
		<forecast></forecast>
		<previous></previous>
		<impact>High</impact>
	</event>
	<event>
		<title>FOMC Member Barr Speaks</title>
		<currency>USD</currency>
		<date>08-02-2023</date>
		<time>10:00am</time>
		<forecast></forecast>
		<previous></previous>
		<impact>Low</impact>
	</event>
	<event>
		<title>Final Wholesale Inventories m/m</title>
		<currency>USD</currency>
		<date>08-02-2023</date>
		<time>10:00am</time>
		<forecast>0.1%</forecast>
		<previous>0.1%</previous>
		<impact>Low</impact>
	</event>
	<event>
		<title>Crude Oil Inventories</title>
		<currency>USD</currency>
		<date>08-02-2023</date>
		<time>10:30am</time>
		<forecast>2.0M</forecast>
		<previous>4.1M</previous>
		<impact>Low</impact>
	</event>
	<event>
		<title>10-y Bond Auction</title>
		<currency>USD</currency>
		<date>08-02-2023</date>
		<time>1:01pm</time>
		<forecast></forecast>
		<previous>3.58|2.5</previous>
		<impact>Medium</impact>
	</event>
	<event>
		<title>BOC Summary of Deliberations</title>
		<currency>CAD</currency>
		<date>08-02-2023</date>
		<time>1:30pm</time>
		<forecast></forecast>
		<previous></previous>
		<impact>Low</impact>
	</event>
	<event>
		<title>FOMC Member Waller Speaks</title>
		<currency>USD</currency>
		<date>08-02-2023</date>
		<time>1:45pm</time>
		<forecast></forecast>
		<previous></previous>
		<impact>Medium</impact>
	</event>
	<event>
		<title>M2 Money Stock y/y</title>
		<currency>JPY</currency>
		<date>08-02-2023</date>
		<time>6:50pm</time>
		<forecast>3.0%</forecast>
		<previous>2.9%</previous>
		<impact>Low</impact>
	</event>
	<event>
		<title>RICS House Price Balance</title>
		<currency>GBP</currency>
		<date>08-02-2023</date>
		<time>7:01pm</time>
		<forecast>-45%</forecast>
		<previous>-42%</previous>
		<impact>Low</impact>
	</event>
	<event>
		<title>Prelim Machine Tool Orders y/y</title>
		<currency>JPY</currency>
		<date>09-02-2023</date>
		<time>12:59am</time>
		<forecast></forecast>
		<previous>0.9%</previous>
		<impact>Low</impact>
	</event>
	<event>
		<title>German Prelim CPI m/m</title>
		<currency>EUR</currency>
		<date>09-02-2023</date>
		<time>All Day</time>
		<forecast>0.9%</forecast>
		<previous>-0.8%</previous>
		<impact>Low</impact>
	</event>
	<event>
		<title>Monetary Policy Report Hearings</title>
		<currency>GBP</currency>
		<date>09-02-2023</date>
		<time>4:45am</time>
		<forecast></forecast>
		<previous></previous>
		<impact>High</impact>
	</event>
	<event>
		<title>Unemployment Claims</title>
		<currency>USD</currency>
		<date>09-02-2023</date>
		<time>8:30am</time>
		<forecast>191K</forecast>
		<previous>183K</previous>
		<impact>Medium</impact>
	</event>
	<event>
		<title>Natural Gas Storage</title>
		<currency>USD</currency>
		<date>09-02-2023</date>
		<time>10:30am</time>
		<forecast>-200B</forecast>
		<previous>-151B</previous>
		<impact>Low</impact>
	</event>
	<event>
		<title>German Buba President Nagel Speaks</title>
		<currency>EUR</currency>
		<date>09-02-2023</date>
		<time>12:00pm</time>
		<forecast></forecast>
		<previous></previous>
		<impact>Low</impact>
	</event>
	<event>
		<title>30-y Bond Auction</title>
		<currency>USD</currency>
		<date>09-02-2023</date>
		<time>1:01pm</time>
		<forecast></forecast>
		<previous>3.59|2.5</previous>
		<impact>Low</impact>
	</event>
	<event>
		<title>BusinessNZ Manufacturing Index</title>
		<currency>NZD</currency>
		<date>09-02-2023</date>
		<time>4:30pm</time>
		<forecast></forecast>
		<previous>47.8</previous>
		<impact>Low</impact>
	</event>
	<event>
		<title>PPI y/y</title>
		<currency>JPY</currency>
		<date>09-02-2023</date>
		<time>6:50pm</time>
		<forecast>9.7%</forecast>
		<previous>10.5%</previous>
		<impact>Low</impact>
	</event>
	<event>
		<title>RBA Monetary Policy Statement</title>
		<currency>AUD</currency>
		<date>09-02-2023</date>
		<time>7:30pm</time>
		<forecast></forecast>
		<previous></previous>
		<impact>Medium</impact>
	</event>
	<event>
		<title>CPI y/y</title>
		<currency>CNY</currency>
		<date>09-02-2023</date>
		<time>8:30pm</time>
		<forecast>2.2%</forecast>
		<previous>1.8%</previous>
		<impact>Low</impact>
	</event>
	<event>
		<title>PPI y/y</title>
		<currency>CNY</currency>
		<date>09-02-2023</date>
		<time>8:30pm</time>
		<forecast>-0.5%</forecast>
		<previous>-0.7%</previous>
		<impact>Low</impact>
	</event>
	<event>
		<title>GDP m/m</title>
		<currency>GBP</currency>
		<date>10-02-2023</date>
		<time>2:00am</time>
		<forecast>-0.3%</forecast>
		<previous>0.1%</previous>
		<impact>High</impact>
	</event>
	<event>
		<title>Prelim GDP q/q</title>
		<currency>GBP</currency>
		<date>10-02-2023</date>
		<time>2:00am</time>
		<forecast>0.0%</forecast>
		<previous>-0.3%</previous>
		<impact>Medium</impact>
	</event>
	<event>
		<title>Construction Output m/m</title>
		<currency>GBP</currency>
		<date>10-02-2023</date>
		<time>2:00am</time>
		<forecast>-0.2%</forecast>
		<previous>-0.5%</previous>
		<impact>Low</impact>
	</event>
	<event>
		<title>Goods Trade Balance</title>
		<currency>GBP</currency>
		<date>10-02-2023</date>
		<time>2:00am</time>
		<forecast>-17.2B</forecast>
		<previous>-14.7B</previous>
		<impact>Low</impact>
	</event>
	<event>
		<title>Index of Services 3m/3m</title>
		<currency>GBP</currency>
		<date>10-02-2023</date>
		<time>2:00am</time>
		<forecast>0.1%</forecast>
		<previous>-0.1%</previous>
		<impact>Low</impact>
	</event>
	<event>
		<title>Industrial Production m/m</title>
		<currency>GBP</currency>
		<date>10-02-2023</date>
		<time>2:00am</time>
		<forecast>-0.2%</forecast>
		<previous>0.1%</previous>
		<impact>Low</impact>
	</event>
	<event>
		<title>Manufacturing Production m/m</title>
		<currency>GBP</currency>
		<date>10-02-2023</date>
		<time>2:00am</time>
		<forecast>-0.2%</forecast>
		<previous>-0.6%</previous>
		<impact>Low</impact>
	</event>
	<event>
		<title>Prelim Business Investment q/q</title>
		<currency>GBP</currency>
		<date>10-02-2023</date>
		<time>2:00am</time>
		<forecast>-0.3%</forecast>
		<previous>-2.5%</previous>
		<impact>Low</impact>
	</event>
	<event>
		<title>Italian Industrial Production m/m</title>
		<currency>EUR</currency>
		<date>10-02-2023</date>
		<time>4:00am</time>
		<forecast>0.2%</forecast>
		<previous>-0.1%</previous>
		<impact>Low</impact>
	</event>
	<event>
		<title>M2 Money Supply y/y</title>
		<currency>CNY</currency>
		<date>10-02-2023</date>
		<time>4:02am</time>
		<forecast>11.6%</forecast>
		<previous>11.8%</previous>
		<impact>Low</impact>
	</event>
	<event>
		<title>New Loans</title>
		<currency>CNY</currency>
		<date>10-02-2023</date>
		<time>4:02am</time>
		<forecast>4200B</forecast>
		<previous>1400B</previous>
		<impact>Low</impact>
	</event>
	<event>
		<title>NIESR GDP Estimate</title>
		<currency>GBP</currency>
		<date>10-02-2023</date>
		<time>7:06am</time>
		<forecast></forecast>
		<previous>0.0%</previous>
		<impact>Low</impact>
	</event>
	<event>
		<title>Employment Change</title>
		<currency>CAD</currency>
		<date>10-02-2023</date>
		<time>8:30am</time>
		<forecast>15.0K</forecast>
		<previous>104.0K</previous>
		<impact>High</impact>
	</event>
	<event>
		<title>Unemployment Rate</title>
		<currency>CAD</currency>
		<date>10-02-2023</date>
		<time>8:30am</time>
		<forecast>5.1%</forecast>
		<previous>5.0%</previous>
		<impact>High</impact>
	</event>
	<event>
		<title>MPC Member Pill Speaks</title>
		<currency>GBP</currency>
		<date>10-02-2023</date>
		<time>9:00am</time>
		<forecast></forecast>
		<previous></previous>
		<impact>Low</impact>
	</event>
	<event>
		<title>Prelim UoM Consumer Sentiment</title>
		<currency>USD</currency>
		<date>10-02-2023</date>
		<time>10:00am</time>
		<forecast>65.0</forecast>
		<previous>64.9</previous>
		<impact>High</impact>
	</event>
	<event>
		<title>Prelim UoM Inflation Expectations</title>
		<currency>USD</currency>
		<date>10-02-2023</date>
		<time>10:00am</time>
		<forecast></forecast>
		<previous>3.9%</previous>
		<impact>Medium</impact>
	</event>
	<event>
		<title>FOMC Member Waller Speaks</title>
		<currency>USD</currency>
		<date>10-02-2023</date>
		<time>12:30pm</time>
		<forecast></forecast>
		<previous></previous>
		<impact>Medium</impact>
	</event>
	<event>
		<title>Federal Budget Balance</title>
		<currency>USD</currency>
		<date>10-02-2023</date>
		<time>2:00pm</time>
		<forecast>-40.5B</forecast>
		<previous>-85.0B</previous>
		<impact>Low</impact>
	</event>
	<event>
		<title>FOMC Member Harker Speaks</title>
		<currency>USD</currency>
		<date>10-02-2023</date>
		<time>4:00pm</time>
		<forecast></forecast>
		<previous></previous>
		<impact>Low</impact>
	</event>
	<event>
		<title/>
		<currency></currency>
		<date>11-02-2023</date>
		<time>4:00pm</time>
		<forecast></forecast>
		<previous></previous>
		<impact></impact>
	</event>
	<event>
		<title>BusinessNZ Services Index</title>
		<currency>NZD</currency>
		<date>12-02-2023</date>
		<time>4:30pm</time>
		<forecast></forecast>
		<previous>52.0</previous>
		<impact>Low</impact>
	</event>
	<event>
		<title>CPI m/m</title>
		<currency>CHF</currency>
		<date>13-02-2023</date>
		<time>2:30am</time>
		<forecast>0.5%</forecast>
		<previous>-0.2%</previous>
		<impact>High</impact>
	</event>
	<event>
		<title>EU Economic Forecasts</title>
		<currency>EUR</currency>
		<date>13-02-2023</date>
		<time>4:00am</time>
		<forecast></forecast>
		<previous></previous>
		<impact>Medium</impact>
	</event>
	<event>
		<title>Eurogroup Meetings</title>
		<currency>EUR</currency>
		<date>13-02-2023</date>
		<time>All Day</time>
		<forecast></forecast>
		<previous></previous>
		<impact>Low</impact>
	</event>
	<event>
		<title>FOMC Member Bowman Speaks</title>
		<currency>USD</currency>
		<date>13-02-2023</date>
		<time>8:00am</time>
		<forecast></forecast>
		<previous></previous>
		<impact>Low</impact>
	</event>
	<event>
		<title>FPI m/m</title>
		<currency>NZD</currency>
		<date>13-02-2023</date>
		<time>4:45pm</time>
		<forecast></forecast>
		<previous>1.1%</previous>
		<impact>Low</impact>
	</event>
	<event>
		<title>Westpac Consumer Sentiment</title>
		<currency>AUD</currency>
		<date>13-02-2023</date>
		<time>6:24pm</time>
		<forecast></forecast>
		<previous>5.0%</previous>
		<impact>Low</impact>
	</event>
	<event>
		<title>Prelim GDP Price Index y/y</title>
		<currency>JPY</currency>
		<date>13-02-2023</date>
		<time>6:50pm</time>
		<forecast>1.1%</forecast>
		<previous>-0.3%</previous>
		<impact>Low</impact>
	</event>
	<event>
		<title>Prelim GDP q/q</title>
		<currency>JPY</currency>
		<date>13-02-2023</date>
		<time>6:50pm</time>
		<forecast>0.5%</forecast>
		<previous>-0.2%</previous>
		<impact>Low</impact>
	</event>
	<event>
		<title>NAB Business Confidence</title>
		<currency>AUD</currency>
		<date>13-02-2023</date>
		<time>7:30pm</time>
		<forecast></forecast>
		<previous>-1</previous>
		<impact>Low</impact>
	</event>
	<event>
		<title>Inflation Expectations q/q</title>
		<currency>NZD</currency>
		<date>13-02-2023</date>
		<time>9:00pm</time>
		<forecast></forecast>
		<previous>3.62%</previous>
		<impact>High</impact>
	</event>
	<event>
		<title>Revised Industrial Production m/m</title>
		<currency>JPY</currency>
		<date>13-02-2023</date>
		<time>11:30pm</time>
		<forecast>-0.1%</forecast>
		<previous>-0.1%</previous>
		<impact>Low</impact>
	</event>
	<event>
		<title>German WPI m/m</title>
		<currency>EUR</currency>
		<date>14-02-2023</date>
		<time>2:00am</time>
		<forecast>1.2%</forecast>
		<previous>-1.6%</previous>
		<impact>Low</impact>
	</event>
	<event>
		<title>Claimant Count Change</title>
		<currency>GBP</currency>
		<date>14-02-2023</date>
		<time>2:00am</time>
		<forecast>17.9K</forecast>
		<previous>-3.2K</previous>
		<impact>High</impact>
	</event>
	<event>
		<title>Average Earnings Index 3m/y</title>
		<currency>GBP</currency>
		<date>14-02-2023</date>
		<time>2:00am</time>
		<forecast>6.2%</forecast>
		<previous>6.5%</previous>
		<impact>Medium</impact>
	</event>
	<event>
		<title>Unemployment Rate</title>
		<currency>GBP</currency>
		<date>14-02-2023</date>
		<time>2:00am</time>
		<forecast>3.7%</forecast>
		<previous>3.7%</previous>
		<impact>Low</impact>
	</event>
	<event>
		<title>PPI m/m</title>
		<currency>CHF</currency>
		<date>14-02-2023</date>
		<time>2:30am</time>
		<forecast>0.2%</forecast>
		<previous>-0.7%</previous>
		<impact>Low</impact>
	</event>
	<event>
		<title>Flash Employment Change q/q</title>
		<currency>EUR</currency>
		<date>14-02-2023</date>
		<time>5:00am</time>
		<forecast>0.1%</forecast>
		<previous>0.3%</previous>
		<impact>Low</impact>
	</event>
	<event>
		<title>Flash GDP q/q</title>
		<currency>EUR</currency>
		<date>14-02-2023</date>
		<time>5:00am</time>
		<forecast>0.1%</forecast>
		<previous>0.1%</previous>
		<impact>Low</impact>
	</event>
	<event>
		<title>10-y Bond Auction</title>
		<currency>GBP</currency>
		<date>14-02-2023</date>
		<time>5:02am</time>
		<forecast></forecast>
		<previous>3.70|2.8</previous>
		<impact>Low</impact>
	</event>
	<event>
		<title>ECOFIN Meetings</title>
		<currency>EUR</currency>
		<date>14-02-2023</date>
		<time>All Day</time>
		<forecast></forecast>
		<previous></previous>
		<impact>Low</impact>
	</event>
	<event>
		<title>NFIB Small Business Index</title>
		<currency>USD</currency>
		<date>14-02-2023</date>
		<time>6:00am</time>
		<forecast>90.9</forecast>
		<previous>89.8</previous>
		<impact>Low</impact>
	</event>
	<event>
		<title>CPI m/m</title>
		<currency>USD</currency>
		<date>14-02-2023</date>
		<time>8:30am</time>
		<forecast>0.5%</forecast>
		<previous>-0.1%</previous>
		<impact>High</impact>
	</event>
	<event>
		<title>CPI y/y</title>
		<currency>USD</currency>
		<date>14-02-2023</date>
		<time>8:30am</time>
		<forecast>6.2%</forecast>
		<previous>6.5%</previous>
		<impact>High</impact>
	</event>
	<event>
		<title>Core CPI m/m</title>
		<currency>USD</currency>
		<date>14-02-2023</date>
		<time>8:30am</time>
		<forecast>0.4%</forecast>
		<previous>0.3%</previous>
		<impact>High</impact>
	</event>
	<event>
		<title>CB Leading Index m/m</title>
		<currency>GBP</currency>
		<date>14-02-2023</date>
		<time>9:30am</time>
		<forecast></forecast>
		<previous>-0.4%</previous>
		<impact>Low</impact>
	</event>
	<event>
		<title>FOMC Member Logan Speaks</title>
		<currency>USD</currency>
		<date>14-02-2023</date>
		<time>11:00am</time>
		<forecast></forecast>
		<previous></previous>
		<impact>Low</impact>
	</event>
	<event>
		<title>FOMC Member Harker Speaks</title>
		<currency>USD</currency>
		<date>14-02-2023</date>
		<time>1:00pm</time>
		<forecast></forecast>
		<previous></previous>
		<impact>Low</impact>
	</event>
	<event>
		<title>FOMC Member Williams Speaks</title>
		<currency>USD</currency>
		<date>14-02-2023</date>
		<time>2:05pm</time>
		<forecast></forecast>
		<previous></previous>
		<impact>Low</impact>
	</event>
	<event>
		<title>RBA Gov Lowe Speaks</title>
		<currency>AUD</currency>
		<date>14-02-2023</date>
		<time>7:15pm</time>
		<forecast></forecast>
		<previous></previous>
		<impact>High</impact>
	</event>
	<event>
		<title>Tertiary Industry Activity m/m</title>
		<currency>JPY</currency>
		<date>14-02-2023</date>
		<time>11:30pm</time>
		<forecast>0.1%</forecast>
		<previous>0.1%</previous>
		<impact>Low</impact>
	</event>
	<event>
		<title>CPI y/y</title>
		<currency>GBP</currency>
		<date>15-02-2023</date>
		<time>2:00am</time>
		<forecast>10.3%</forecast>
		<previous>10.5%</previous>
		<impact>High</impact>
	</event>
	<event>
		<title>Core CPI y/y</title>
		<currency>GBP</currency>
		<date>15-02-2023</date>
		<time>2:00am</time>
		<forecast>6.2%</forecast>
		<previous>6.3%</previous>
		<impact>Low</impact>
	</event>
	<event>
		<title>PPI Input m/m</title>
		<currency>GBP</currency>
		<date>15-02-2023</date>
		<time>2:00am</time>
		<forecast>0.2%</forecast>
		<previous>-1.1%</previous>
		<impact>Low</impact>
	</event>
	<event>
		<title>PPI Output m/m</title>
		<currency>GBP</currency>
		<date>15-02-2023</date>
		<time>2:00am</time>
		<forecast>0.1%</forecast>
		<previous>-0.8%</previous>
		<impact>Low</impact>
	</event>
	<event>
		<title>RPI y/y</title>
		<currency>GBP</currency>
		<date>15-02-2023</date>
		<time>2:00am</time>
		<forecast>13.2%</forecast>
		<previous>13.4%</previous>
		<impact>Low</impact>
	</event>
	<event>
		<title>HPI y/y</title>
		<currency>GBP</currency>
		<date>15-02-2023</date>
		<time>4:30am</time>
		<forecast>9.2%</forecast>
		<previous>10.6%</previous>
		<impact>Low</impact>
	</event>
	<event>
		<title>Industrial Production m/m</title>
		<currency>EUR</currency>
		<date>15-02-2023</date>
		<time>5:00am</time>
		<forecast>-0.8%</forecast>
		<previous>1.4%</previous>
		<impact>Low</impact>
	</event>
	<event>
		<title>Trade Balance</title>
		<currency>EUR</currency>
		<date>15-02-2023</date>
		<time>5:00am</time>
		<forecast>-16.0B</forecast>
		<previous>-14.4B</previous>
		<impact>Low</impact>
	</event>
	<event>
		<title>German 30-y Bond Auction</title>
		<currency>EUR</currency>
		<date>15-02-2023</date>
		<time>5:40am</time>
		<forecast></forecast>
		<previous>2.05|1.5</previous>
		<impact>Low</impact>
	</event>
	<event>
		<title>Housing Starts</title>
		<currency>CAD</currency>
		<date>15-02-2023</date>
		<time>8:14am</time>
		<forecast>246K</forecast>
		<previous>248K</previous>
		<impact>Low</impact>
	</event>
	<event>
		<title>Manufacturing Sales m/m</title>
		<currency>CAD</currency>
		<date>15-02-2023</date>
		<time>8:30am</time>
		<forecast>-1.6%</forecast>
		<previous>-0.2%</previous>
		<impact>Low</impact>
	</event>
	<event>
		<title>Wholesale Sales m/m</title>
		<currency>CAD</currency>
		<date>15-02-2023</date>
		<time>8:30am</time>
		<forecast>-1.5%</forecast>
		<previous>-0.7%</previous>
		<impact>Low</impact>
	</event>
	<event>
		<title>Core Retail Sales m/m</title>
		<currency>USD</currency>
		<date>15-02-2023</date>
		<time>8:30am</time>
		<forecast>0.9%</forecast>
		<previous>-0.9%</previous>
		<impact>High</impact>
	</event>
	<event>
		<title>Empire State Manufacturing Index</title>
		<currency>USD</currency>
		<date>15-02-2023</date>
		<time>8:30am</time>
		<forecast>-18.2</forecast>
		<previous>-32.9</previous>
		<impact>High</impact>
	</event>
	<event>
		<title>Retail Sales m/m</title>
		<currency>USD</currency>
		<date>15-02-2023</date>
		<time>8:30am</time>
		<forecast>1.9%</forecast>
		<previous>-1.1%</previous>
		<impact>High</impact>
	</event>
	<event>
		<title>Capacity Utilization Rate</title>
		<currency>USD</currency>
		<date>15-02-2023</date>
		<time>9:15am</time>
		<forecast>79.1%</forecast>
		<previous>78.4%</previous>
		<impact>Low</impact>
	</event>
	<event>
		<title>Industrial Production m/m</title>
		<currency>USD</currency>
		<date>15-02-2023</date>
		<time>9:15am</time>
		<forecast>0.5%</forecast>
		<previous>-1.0%</previous>
		<impact>Low</impact>
	</event>
	<event>
		<title>Business Inventories m/m</title>
		<currency>USD</currency>
		<date>15-02-2023</date>
		<time>10:00am</time>
		<forecast>0.3%</forecast>
		<previous>0.3%</previous>
		<impact>Low</impact>
	</event>
	<event>
		<title>NAHB Housing Market Index</title>
		<currency>USD</currency>
		<date>15-02-2023</date>
		<time>10:00am</time>
		<forecast>37</forecast>
		<previous>35</previous>
		<impact>Low</impact>
	</event>
	<event>
		<title>Crude Oil Inventories</title>
		<currency>USD</currency>
		<date>15-02-2023</date>
		<time>10:30am</time>
		<forecast>1.5M</forecast>
		<previous>2.4M</previous>
		<impact>Low</impact>
	</event>
	<event>
		<title>ECB President Lagarde Speaks</title>
		<currency>EUR</currency>
		<date>15-02-2023</date>
		<time>12:15pm</time>
		<forecast></forecast>
		<previous></previous>
		<impact>Medium</impact>
	</event>
	<event>
		<title>TIC Long-Term Purchases</title>
		<currency>USD</currency>
		<date>15-02-2023</date>
		<time>4:00pm</time>
		<forecast>119.1B</forecast>
		<previous>171.5B</previous>
		<impact>Low</impact>
	</event>
	<event>
		<title>Visitor Arrivals m/m</title>
		<currency>NZD</currency>
		<date>15-02-2023</date>
		<time>4:45pm</time>
		<forecast></forecast>
		<previous>43.1%</previous>
		<impact>Low</impact>
	</event>
	<event>
		<title>Core Machinery Orders m/m</title>
		<currency>JPY</currency>
		<date>15-02-2023</date>
		<time>6:50pm</time>
		<forecast>2.7%</forecast>
		<previous>-8.3%</previous>
		<impact>Low</impact>
	</event>
	<event>
		<title>Trade Balance</title>
		<currency>JPY</currency>
		<date>15-02-2023</date>
		<time>6:50pm</time>
		<forecast>-2.35T</forecast>
		<previous>-1.82T</previous>
		<impact>Low</impact>
	</event>
	<event>
		<title>MI Inflation Expectations</title>
		<currency>AUD</currency>
		<date>15-02-2023</date>
		<time>7:00pm</time>
		<forecast></forecast>
		<previous>5.6%</previous>
		<impact>Low</impact>
	</event>
	<event>
		<title>Employment Change</title>
		<currency>AUD</currency>
		<date>15-02-2023</date>
		<time>7:30pm</time>
		<forecast>19.8K</forecast>
		<previous>-20.0K</previous>
		<impact>High</impact>
	</event>
	<event>
		<title>Unemployment Rate</title>
		<currency>AUD</currency>
		<date>15-02-2023</date>
		<time>7:30pm</time>
		<forecast>3.5%</forecast>
		<previous>3.5%</previous>
		<impact>High</impact>
	</event>
	<event>
		<title>ECB Economic Bulletin</title>
		<currency>EUR</currency>
		<date>16-02-2023</date>
		<time>4:00am</time>
		<forecast></forecast>
		<previous></previous>
		<impact>Low</impact>
	</event>
	<event>
		<title>Italian Trade Balance</title>
		<currency>EUR</currency>
		<date>16-02-2023</date>
		<time>4:00am</time>
		<forecast>1.40B</forecast>
		<previous>1.42B</previous>
		<impact>Low</impact>
	</event>
	<event>
		<title>Spanish 10-y Bond Auction</title>
		<currency>EUR</currency>
		<date>16-02-2023</date>
		<time>4:46am</time>
		<forecast></forecast>
		<previous>2.66|2.2</previous>
		<impact>Low</impact>
	</event>
	<event>
		<title>German Buba President Nagel Speaks</title>
		<currency>EUR</currency>
		<date>16-02-2023</date>
		<time>8:00am</time>
		<forecast></forecast>
		<previous></previous>
		<impact>Low</impact>
	</event>
	<event>
		<title>Core PPI m/m</title>
		<currency>USD</currency>
		<date>16-02-2023</date>
		<time>8:30am</time>
		<forecast>0.3%</forecast>
		<previous>0.3%</previous>
		<impact>High</impact>
	</event>
	<event>
		<title>PPI m/m</title>
		<currency>USD</currency>
		<date>16-02-2023</date>
		<time>8:30am</time>
		<forecast>0.4%</forecast>
		<previous>-0.2%</previous>
		<impact>High</impact>
	</event>
	<event>
		<title>Philly Fed Manufacturing Index</title>
		<currency>USD</currency>
		<date>16-02-2023</date>
		<time>8:30am</time>
		<forecast>-7.6</forecast>
		<previous>-8.9</previous>
		<impact>Medium</impact>
	</event>
	<event>
		<title>Unemployment Claims</title>
		<currency>USD</currency>
		<date>16-02-2023</date>
		<time>8:30am</time>
		<forecast>200K</forecast>
		<previous>195K</previous>
		<impact>Medium</impact>
	</event>
	<event>
		<title>Building Permits</title>
		<currency>USD</currency>
		<date>16-02-2023</date>
		<time>8:30am</time>
		<forecast>1.35M</forecast>
		<previous>1.34M</previous>
		<impact>Low</impact>
	</event>
	<event>
		<title>Housing Starts</title>
		<currency>USD</currency>
		<date>16-02-2023</date>
		<time>8:30am</time>
		<forecast>1.35M</forecast>
		<previous>1.37M</previous>
		<impact>Low</impact>
	</event>
	<event>
		<title>Mortgage Delinquencies</title>
		<currency>USD</currency>
		<date>16-02-2023</date>
		<time>10:00am</time>
		<forecast></forecast>
		<previous>3.45%</previous>
		<impact>Low</impact>
	</event>
	<event>
		<title>CB Leading Index m/m</title>
		<currency>AUD</currency>
		<date>16-02-2023</date>
		<time>10:30am</time>
		<forecast></forecast>
		<previous>0.1%</previous>
		<impact>Low</impact>
	</event>
	<event>
		<title>Natural Gas Storage</title>
		<currency>USD</currency>
		<date>16-02-2023</date>
		<time>10:30am</time>
		<forecast>-97B</forecast>
		<previous>-217B</previous>
		<impact>Low</impact>
	</event>
	<event>
		<title>BOC Gov Macklem Speaks</title>
		<currency>CAD</currency>
		<date>16-02-2023</date>
		<time>11:00am</time>
		<forecast></forecast>
		<previous></previous>
		<impact>High</impact>
	</event>
	<event>
		<title>MPC Member Pill Speaks</title>
		<currency>GBP</currency>
		<date>16-02-2023</date>
		<time>12:00pm</time>
		<forecast></forecast>
		<previous></previous>
		<impact>Low</impact>
	</event>
	<event>
		<title>FOMC Member Cook Speaks</title>
		<currency>USD</currency>
		<date>16-02-2023</date>
		<time>4:00pm</time>
		<forecast></forecast>
		<previous></previous>
		<impact>Low</impact>
	</event>
	<event>
		<title>RBA Gov Lowe Speaks</title>
		<currency>AUD</currency>
		<date>16-02-2023</date>
		<time>5:30pm</time>
		<forecast></forecast>
		<previous></previous>
		<impact>High</impact>
	</event>
	<event>
		<title>Gov Council Member Beaudry Speaks</title>
		<currency>CAD</currency>
		<date>16-02-2023</date>
		<time>5:55pm</time>
		<forecast></forecast>
		<previous></previous>
		<impact>Low</impact>
	</event>
	<event>
		<title>German PPI m/m</title>
		<currency>EUR</currency>
		<date>17-02-2023</date>
		<time>2:00am</time>
		<forecast>0.2%</forecast>
		<previous>-0.4%</previous>
		<impact>Low</impact>
	</event>
	<event>
		<title>Retail Sales m/m</title>
		<currency>GBP</currency>
		<date>17-02-2023</date>
		<time>2:00am</time>
		<forecast>-0.3%</forecast>
		<previous>-1.2%</previous>
		<impact>Medium</impact>
	</event>
	<event>
		<title>French Final CPI m/m</title>
		<currency>EUR</currency>
		<date>17-02-2023</date>
		<time>2:45am</time>
		<forecast>0.4%</forecast>
		<previous>0.4%</previous>
		<impact>Low</impact>
	</event>
	<event>
		<title>Current Account</title>
		<currency>EUR</currency>
		<date>17-02-2023</date>
		<time>4:00am</time>
		<forecast>5.1B</forecast>
		<previous>12.8B</previous>
		<impact>Low</impact>
	</event>
	<event>
		<title>Foreign Securities Purchases</title>
		<currency>CAD</currency>
		<date>17-02-2023</date>
		<time>8:30am</time>
		<forecast>-1.25B</forecast>
		<previous>12.40B</previous>
		<impact>Low</impact>
	</event>
	<event>
		<title>IPPI m/m</title>
		<currency>CAD</currency>
		<date>17-02-2023</date>
		<time>8:30am</time>
		<forecast>-0.1%</forecast>
		<previous>-0.9%</previous>
		<impact>Low</impact>
	</event>
	<event>
		<title>RMPI m/m</title>
		<currency>CAD</currency>
		<date>17-02-2023</date>
		<time>8:30am</time>
		<forecast>-0.2%</forecast>
		<previous>-2.8%</previous>
		<impact>Low</impact>
	</event>
	<event>
		<title>Import Prices m/m</title>
		<currency>USD</currency>
		<date>17-02-2023</date>
		<time>8:30am</time>
		<forecast>-0.1%</forecast>
		<previous>-0.1%</previous>
		<impact>Low</impact>
	</event>
	<event>
		<title>FOMC Member Bowman Speaks</title>
		<currency>USD</currency>
		<date>17-02-2023</date>
		<time>9:45am</time>
		<forecast></forecast>
		<previous></previous>
		<impact>Low</impact>
	</event>
	<event>
		<title>CB Leading Index m/m</title>
		<currency>USD</currency>
		<date>17-02-2023</date>
		<time>10:00am</time>
		<forecast>-0.3%</forecast>
		<previous>-0.8%</previous>
		<impact>Low</impact>
	</event>
	<event>
		<title>German Buba President Nagel Speaks</title>
		<currency>EUR</currency>
		<date>18-02-2023</date>
		<time>11:30am</time>
		<forecast></forecast>
		<previous></previous>
		<impact>Low</impact>
	</event>
	<event>
		<title>Rightmove HPI m/m</title>
		<currency>GBP</currency>
		<date>19-02-2023</date>
		<time>7:01pm</time>
		<forecast></forecast>
		<previous>0.9%</previous>
		<impact>Low</impact>
	</event>
	<event>
		<title>Foreign Direct Investment ytd/y</title>
		<currency>CNY</currency>
		<date>20-02-2023</date>
		<time>5:45am</time>
		<forecast></forecast>
		<previous>6.3%</previous>
		<impact>Low</impact>
	</event>
	<event>
		<title>German Buba Monthly Report</title>
		<currency>EUR</currency>
		<date>20-02-2023</date>
		<time>6:00am</time>
		<forecast></forecast>
		<previous></previous>
		<impact>Low</impact>
	</event>
	<event>
		<title>Bank Holiday</title>
		<currency>CAD</currency>
		<date>20-02-2023</date>
		<time>All Day</time>
		<forecast></forecast>
		<previous></previous>
		<impact>Holiday</impact>
	</event>
	<event>
		<title>Bank Holiday</title>
		<currency>USD</currency>
		<date>20-02-2023</date>
		<time>All Day</time>
		<forecast></forecast>
		<previous></previous>
		<impact>Holiday</impact>
	</event>
	<event>
		<title>Consumer Confidence</title>
		<currency>EUR</currency>
		<date>20-02-2023</date>
		<time>10:00am</time>
		<forecast>-19</forecast>
		<previous>-21</previous>
		<impact>Low</impact>
	</event>
	<event>
		<title>PPI Input q/q</title>
		<currency>NZD</currency>
		<date>20-02-2023</date>
		<time>4:45pm</time>
		<forecast>0.5%</forecast>
		<previous>0.8%</previous>
		<impact>Low</impact>
	</event>
	<event>
		<title>PPI Output q/q</title>
		<currency>NZD</currency>
		<date>20-02-2023</date>
		<time>4:45pm</time>
		<forecast>0.4%</forecast>
		<previous>1.6%</previous>
		<impact>Low</impact>
	</event>
	<event>
		<title>Flash Manufacturing PMI</title>
		<currency>AUD</currency>
		<date>20-02-2023</date>
		<time>5:00pm</time>
		<forecast></forecast>
		<previous>50.0</previous>
		<impact>Low</impact>
	</event>
	<event>
		<title>Flash Services PMI</title>
		<currency>AUD</currency>
		<date>20-02-2023</date>
		<time>5:00pm</time>
		<forecast></forecast>
		<previous>48.6</previous>
		<impact>Low</impact>
	</event>
	<event>
		<title>Monetary Policy Meeting Minutes</title>
		<currency>AUD</currency>
		<date>20-02-2023</date>
		<time>7:30pm</time>
		<forecast></forecast>
		<previous></previous>
		<impact>Medium</impact>
	</event>
	<event>
		<title>Flash Manufacturing PMI</title>
		<currency>JPY</currency>
		<date>20-02-2023</date>
		<time>7:30pm</time>
		<forecast>49.3</forecast>
		<previous>48.9</previous>
		<impact>Low</impact>
	</event>
	<event>
		<title>Trade Balance</title>
		<currency>CHF</currency>
		<date>21-02-2023</date>
		<time>2:00am</time>
		<forecast>3.75B</forecast>
		<previous>2.77B</previous>
		<impact>Low</impact>
	</event>
	<event>
		<title>Public Sector Net Borrowing</title>
		<currency>GBP</currency>
		<date>21-02-2023</date>
		<time>2:00am</time>
		<forecast>2.0B</forecast>
		<previous>24.8B</previous>
		<impact>Low</impact>
	</event>
	<event>
		<title>French Flash Manufacturing PMI</title>
		<currency>EUR</currency>
		<date>21-02-2023</date>
		<time>3:15am</time>
		<forecast>51.0</forecast>
		<previous>50.5</previous>
		<impact>Medium</impact>
	</event>
	<event>
		<title>French Flash Services PMI</title>
		<currency>EUR</currency>
		<date>21-02-2023</date>
		<time>3:15am</time>
		<forecast>49.7</forecast>
		<previous>49.4</previous>
		<impact>Medium</impact>
	</event>
	<event>
		<title>German Flash Manufacturing PMI</title>
		<currency>EUR</currency>
		<date>21-02-2023</date>
		<time>3:30am</time>
		<forecast>48.0</forecast>
		<previous>47.3</previous>
		<impact>Medium</impact>
	</event>
	<event>
		<title>German Flash Services PMI</title>
		<currency>EUR</currency>
		<date>21-02-2023</date>
		<time>3:30am</time>
		<forecast>51.0</forecast>
		<previous>50.7</previous>
		<impact>Medium</impact>
	</event>
	<event>
		<title>Flash Manufacturing PMI</title>
		<currency>EUR</currency>
		<date>21-02-2023</date>
		<time>4:00am</time>
		<forecast>49.4</forecast>
		<previous>48.8</previous>
		<impact>Low</impact>
	</event>
	<event>
		<title>Flash Services PMI</title>
		<currency>EUR</currency>
		<date>21-02-2023</date>
		<time>4:00am</time>
		<forecast>51.0</forecast>
		<previous>50.8</previous>
		<impact>Low</impact>
	</event>
	<event>
		<title>Flash Manufacturing PMI</title>
		<currency>GBP</currency>
		<date>21-02-2023</date>
		<time>4:30am</time>
		<forecast>47.5</forecast>
		<previous>47.0</previous>
		<impact>High</impact>
	</event>
	<event>
		<title>Flash Services PMI</title>
		<currency>GBP</currency>
		<date>21-02-2023</date>
		<time>4:30am</time>
		<forecast>49.2</forecast>
		<previous>48.7</previous>
		<impact>High</impact>
	</event>
	<event>
		<title>German ZEW Economic Sentiment</title>
		<currency>EUR</currency>
		<date>21-02-2023</date>
		<time>5:00am</time>
		<forecast>22.8</forecast>
		<previous>16.9</previous>
		<impact>Medium</impact>
	</event>
	<event>
		<title>ZEW Economic Sentiment</title>
		<currency>EUR</currency>
		<date>21-02-2023</date>
		<time>5:00am</time>
		<forecast>22.3</forecast>
		<previous>16.7</previous>
		<impact>Low</impact>
	</event>
	<event>
		<title>CBI Industrial Order Expectations</title>
		<currency>GBP</currency>
		<date>21-02-2023</date>
		<time>6:00am</time>
		<forecast>-14</forecast>
		<previous>-17</previous>
		<impact>Low</impact>
	</event>
	<event>
		<title>CPI m/m</title>
		<currency>CAD</currency>
		<date>21-02-2023</date>
		<time>8:30am</time>
		<forecast>0.7%</forecast>
		<previous>-0.6%</previous>
		<impact>High</impact>
	</event>
	<event>
		<title>Median CPI y/y</title>
		<currency>CAD</currency>
		<date>21-02-2023</date>
		<time>8:30am</time>
		<forecast>4.9%</forecast>
		<previous>5.2%</previous>
		<impact>High</impact>
	</event>
	<event>
		<title>Trimmed CPI y/y</title>
		<currency>CAD</currency>
		<date>21-02-2023</date>
		<time>8:30am</time>
		<forecast>5.2%</forecast>
		<previous>5.3%</previous>
		<impact>High</impact>
	</event>
	<event>
		<title>Core Retail Sales m/m</title>
		<currency>CAD</currency>
		<date>21-02-2023</date>
		<time>8:30am</time>
		<forecast>-0.1%</forecast>
		<previous>-0.5%</previous>
		<impact>Medium</impact>
	</event>
	<event>
		<title>Retail Sales m/m</title>
		<currency>CAD</currency>
		<date>21-02-2023</date>
		<time>8:30am</time>
		<forecast>0.5%</forecast>
		<previous>0.0%</previous>
		<impact>Medium</impact>
	</event>
	<event>
		<title>Common CPI y/y</title>
		<currency>CAD</currency>
		<date>21-02-2023</date>
		<time>8:32am</time>
		<forecast>6.5%</forecast>
		<previous>6.6%</previous>
		<impact>Medium</impact>
	</event>
	<event>
		<title>Core CPI m/m</title>
		<currency>CAD</currency>
		<date>21-02-2023</date>
		<time>8:32am</time>
		<forecast></forecast>
		<previous>-0.3%</previous>
		<impact>Low</impact>
	</event>
	<event>
		<title>GDT Price Index</title>
		<currency>NZD</currency>
		<date>21-02-2023</date>
		<time>9:45am</time>
		<forecast></forecast>
		<previous>3.2%</previous>
		<impact>Low</impact>
	</event>
	<event>
		<title>Flash Services PMI</title>
		<currency>USD</currency>
		<date>21-02-2023</date>
		<time>9:45am</time>
		<forecast>47.3</forecast>
		<previous>46.8</previous>
		<impact>High</impact>
	</event>
	<event>
		<title>Flash Manufacturing PMI</title>
		<currency>USD</currency>
		<date>21-02-2023</date>
		<time>9:45am</time>
		<forecast>47.4</forecast>
		<previous>46.9</previous>
		<impact>Medium</impact>
	</event>
	<event>
		<title>Existing Home Sales</title>
		<currency>USD</currency>
		<date>21-02-2023</date>
		<time>10:00am</time>
		<forecast>4.09M</forecast>
		<previous>4.03M</previous>
		<impact>Medium</impact>
	</event>
	<event>
		<title>Trade Balance</title>
		<currency>NZD</currency>
		<date>21-02-2023</date>
		<time>4:45pm</time>
		<forecast>-785M</forecast>
		<previous>-636M</previous>
		<impact>Low</impact>
	</event>
	<event>
		<title>MI Leading Index m/m</title>
		<currency>AUD</currency>
		<date>21-02-2023</date>
		<time>6:30pm</time>
		<forecast></forecast>
		<previous>-0.2%</previous>
		<impact>Low</impact>
	</event>
	<event>
		<title>SPPI y/y</title>
		<currency>JPY</currency>
		<date>21-02-2023</date>
		<time>6:50pm</time>
		<forecast>1.5%</forecast>
		<previous>1.5%</previous>
		<impact>Low</impact>
	</event>
	<event>
		<title>Wage Price Index q/q</title>
		<currency>AUD</currency>
		<date>21-02-2023</date>
		<time>7:30pm</time>
		<forecast>1.0%</forecast>
		<previous>1.1%</previous>
		<impact>High</impact>
	</event>
	<event>
		<title>Construction Work Done q/q</title>
		<currency>AUD</currency>
		<date>21-02-2023</date>
		<time>7:30pm</time>
		<forecast>1.6%</forecast>
		<previous>3.7%</previous>
		<impact>Low</impact>
	</event>
	<event>
		<title>Official Cash Rate</title>
		<currency>NZD</currency>
		<date>21-02-2023</date>
		<time>8:00pm</time>
		<forecast>4.75%</forecast>
		<previous>4.25%</previous>
		<impact>High</impact>
	</event>
	<event>
		<title>RBNZ Monetary Policy Statement</title>
		<currency>NZD</currency>
		<date>21-02-2023</date>
		<time>8:00pm</time>
		<forecast></forecast>
		<previous></previous>
		<impact>High</impact>
	</event>
	<event>
		<title>RBNZ Rate Statement</title>
		<currency>NZD</currency>
		<date>21-02-2023</date>
		<time>8:00pm</time>
		<forecast></forecast>
		<previous></previous>
		<impact>High</impact>
	</event>
	<event>
		<title>RBNZ Press Conference</title>
		<currency>NZD</currency>
		<date>21-02-2023</date>
		<time>9:00pm</time>
		<forecast></forecast>
		<previous></previous>
		<impact>High</impact>
	</event>
	<event>
		<title>Credit Card Spending y/y</title>
		<currency>NZD</currency>
		<date>21-02-2023</date>
		<time>9:00pm</time>
		<forecast></forecast>
		<previous>12.7%</previous>
		<impact>Low</impact>
	</event>
	<event>
		<title>German Final CPI m/m</title>
		<currency>EUR</currency>
		<date>22-02-2023</date>
		<time>2:00am</time>
		<forecast>1.0%</forecast>
		<previous>1.0%</previous>
		<impact>Low</impact>
	</event>
	<event>
		<title>Credit Suisse Economic Expectations</title>
		<currency>CHF</currency>
		<date>22-02-2023</date>
		<time>4:00am</time>
		<forecast></forecast>
		<previous>-40.0</previous>
		<impact>Low</impact>
	</event>
	<event>
		<title>German ifo Business Climate</title>
		<currency>EUR</currency>
		<date>22-02-2023</date>
		<time>4:00am</time>
		<forecast>91.1</forecast>
		<previous>90.2</previous>
		<impact>Medium</impact>
	</event>
	<event>
		<title>German 10-y Bond Auction</title>
		<currency>EUR</currency>
		<date>22-02-2023</date>
		<time>5:35am</time>
		<forecast></forecast>
		<previous>2.27|1.5</previous>
		<impact>Low</impact>
	</event>
	<event>
		<title>NHPI m/m</title>
		<currency>CAD</currency>
		<date>22-02-2023</date>
		<time>8:30am</time>
		<forecast>0.1%</forecast>
		<previous>0.0%</previous>
		<impact>Low</impact>
	</event>
	<event>
		<title>Belgian NBB Business Climate</title>
		<currency>EUR</currency>
		<date>22-02-2023</date>
		<time>9:00am</time>
		<forecast>-12.0</forecast>
		<previous>-13.5</previous>
		<impact>Low</impact>
	</event>
	<event>
		<title>G20 Meetings</title>
		<currency>All</currency>
		<date>22-02-2023</date>
		<time>Day 1</time>
		<forecast></forecast>
		<previous></previous>
		<impact>Medium</impact>
	</event>
	<event>
		<title>FOMC Meeting Minutes</title>
		<currency>USD</currency>
		<date>22-02-2023</date>
		<time>2:00pm</time>
		<forecast></forecast>
		<previous></previous>
		<impact>High</impact>
	</event>
	<event>
		<title>RBNZ Gov Orr Speaks</title>
		<currency>NZD</currency>
		<date>22-02-2023</date>
		<time>2:10pm</time>
		<forecast></forecast>
		<previous></previous>
		<impact>High</impact>
	</event>
	<event>
		<title>FOMC Member Williams Speaks</title>
		<currency>USD</currency>
		<date>22-02-2023</date>
		<time>5:30pm</time>
		<forecast></forecast>
		<previous></previous>
		<impact>Low</impact>
	</event>
	<event>
		<title>Bank Holiday</title>
		<currency>JPY</currency>
		<date>22-02-2023</date>
		<time>All Day</time>
		<forecast></forecast>
		<previous></previous>
		<impact>Holiday</impact>
	</event>
	<event>
		<title>Private Capital Expenditure q/q</title>
		<currency>AUD</currency>
		<date>22-02-2023</date>
		<time>7:30pm</time>
		<forecast>1.1%</forecast>
		<previous>-0.6%</previous>
		<impact>Low</impact>
	</event>
	<event>
		<title>RBA Deputy Gov Bullock Speaks</title>
		<currency>AUD</currency>
		<date>23-02-2023</date>
		<time>12:15am</time>
		<forecast></forecast>
		<previous></previous>
		<impact>Low</impact>
	</event>
	<event>
		<title>MPC Member Mann Speaks</title>
		<currency>GBP</currency>
		<date>23-02-2023</date>
		<time>4:30am</time>
		<forecast></forecast>
		<previous></previous>
		<impact>Low</impact>
	</event>
	<event>
		<title>Final CPI y/y</title>
		<currency>EUR</currency>
		<date>23-02-2023</date>
		<time>5:00am</time>
		<forecast>8.6%</forecast>
		<previous>8.5%</previous>
		<impact>Low</impact>
	</event>
	<event>
		<title>Final Core CPI y/y</title>
		<currency>EUR</currency>
		<date>23-02-2023</date>
		<time>5:00am</time>
		<forecast>5.2%</forecast>
		<previous>5.2%</previous>
		<impact>Low</impact>
	</event>
	<event>
		<title>MPC Member Cunliffe Speaks</title>
		<currency>GBP</currency>
		<date>23-02-2023</date>
		<time>5:45am</time>
		<forecast></forecast>
		<previous></previous>
		<impact>Low</impact>
	</event>
	<event>
		<title>CBI Realized Sales</title>
		<currency>GBP</currency>
		<date>23-02-2023</date>
		<time>6:00am</time>
		<forecast>-11</forecast>
		<previous>-23</previous>
		<impact>Low</impact>
	</event>
	<event>
		<title>Corporate Profits q/q</title>
		<currency>CAD</currency>
		<date>23-02-2023</date>
		<time>8:30am</time>
		<forecast></forecast>
		<previous>-8.1%</previous>
		<impact>Low</impact>
	</event>
	<event>
		<title>Prelim GDP q/q</title>
		<currency>USD</currency>
		<date>23-02-2023</date>
		<time>8:30am</time>
		<forecast>2.9%</forecast>
		<previous>2.9%</previous>
		<impact>High</impact>
	</event>
	<event>
		<title>Unemployment Claims</title>
		<currency>USD</currency>
		<date>23-02-2023</date>
		<time>8:30am</time>
		<forecast>200K</forecast>
		<previous>194K</previous>
		<impact>Medium</impact>
	</event>
	<event>
		<title>Prelim GDP Price Index q/q</title>
		<currency>USD</currency>
		<date>23-02-2023</date>
		<time>8:30am</time>
		<forecast>3.5%</forecast>
		<previous>3.5%</previous>
		<impact>Low</impact>
	</event>
	<event>
		<title>CB Leading Index m/m</title>
		<currency>CNY</currency>
		<date>23-02-2023</date>
		<time>9:00am</time>
		<forecast></forecast>
		<previous>-0.8%</previous>
		<impact>Low</impact>
	</event>
	<event>
		<title>G20 Meetings</title>
		<currency>All</currency>
		<date>23-02-2023</date>
		<time>Day 2</time>
		<forecast></forecast>
		<previous></previous>
		<impact>Medium</impact>
	</event>
	<event>
		<title>Natural Gas Storage</title>
		<currency>USD</currency>
		<date>23-02-2023</date>
		<time>10:30am</time>
		<forecast>-60B</forecast>
		<previous>-100B</previous>
		<impact>Low</impact>
	</event>
	<event>
		<title>Crude Oil Inventories</title>
		<currency>USD</currency>
		<date>23-02-2023</date>
		<time>11:00am</time>
		<forecast>2.9M</forecast>
		<previous>16.3M</previous>
		<impact>Low</impact>
	</event>
	<event>
		<title>National Core CPI y/y</title>
		<currency>JPY</currency>
		<date>23-02-2023</date>
		<time>6:30pm</time>
		<forecast>4.3%</forecast>
		<previous>4.0%</previous>
		<impact>Low</impact>
	</event>
	<event>
		<title>GfK Consumer Confidence</title>
		<currency>GBP</currency>
		<date>23-02-2023</date>
		<time>7:01pm</time>
		<forecast>-43</forecast>
		<previous>-45</previous>
		<impact>Low</impact>
	</event>
	<event>
		<title>German Final GDP q/q</title>
		<currency>EUR</currency>
		<date>24-02-2023</date>
		<time>2:00am</time>
		<forecast>-0.2%</forecast>
		<previous>-0.2%</previous>
		<impact>Low</impact>
	</event>
	<event>
		<title>German GfK Consumer Climate</title>
		<currency>EUR</currency>
		<date>24-02-2023</date>
		<time>2:00am</time>
		<forecast>-30.6</forecast>
		<previous>-33.9</previous>
		<impact>Low</impact>
	</event>
	<event>
		<title>BOJ Gov-Designate Ueda Speaks</title>
		<currency>JPY</currency>
		<date>24-02-2023</date>
		<time>Tentative</time>
		<forecast></forecast>
		<previous></previous>
		<impact>High</impact>
	</event>
	<event>
		<title>Italian 10-y Bond Auction</title>
		<currency>EUR</currency>
		<date>24-02-2023</date>
		<time>Tentative</time>
		<forecast></forecast>
		<previous>4.28|1.3</previous>
		<impact>Low</impact>
	</event>
	<event>
		<title>Core PCE Price Index m/m</title>
		<currency>USD</currency>
		<date>24-02-2023</date>
		<time>8:30am</time>
		<forecast>0.4%</forecast>
		<previous>0.3%</previous>
		<impact>High</impact>
	</event>
	<event>
		<title>Personal Income m/m</title>
		<currency>USD</currency>
		<date>24-02-2023</date>
		<time>8:30am</time>
		<forecast>1.0%</forecast>
		<previous>0.2%</previous>
		<impact>Low</impact>
	</event>
	<event>
		<title>Personal Spending m/m</title>
		<currency>USD</currency>
		<date>24-02-2023</date>
		<time>8:30am</time>
		<forecast>1.4%</forecast>
		<previous>-0.2%</previous>
		<impact>Low</impact>
	</event>
	<event>
		<title>New Home Sales</title>
		<currency>USD</currency>
		<date>24-02-2023</date>
		<time>10:00am</time>
		<forecast>620K</forecast>
		<previous>616K</previous>
		<impact>Medium</impact>
	</event>
	<event>
		<title>Revised UoM Consumer Sentiment</title>
		<currency>USD</currency>
		<date>24-02-2023</date>
		<time>10:00am</time>
		<forecast>66.4</forecast>
		<previous>66.4</previous>
		<impact>Medium</impact>
	</event>
	<event>
		<title>Revised UoM Inflation Expectations</title>
		<currency>USD</currency>
		<date>24-02-2023</date>
		<time>10:00am</time>
		<forecast></forecast>
		<previous>4.2%</previous>
		<impact>Low</impact>
	</event>
	<event>
		<title>G20 Meetings</title>
		<currency>All</currency>
		<date>24-02-2023</date>
		<time>Day 3</time>
		<forecast></forecast>
		<previous></previous>
		<impact>Medium</impact>
	</event>
	<event>
		<title>FOMC Member Jefferson Speaks</title>
		<currency>USD</currency>
		<date>24-02-2023</date>
		<time>10:15am</time>
		<forecast></forecast>
		<previous></previous>
		<impact>Low</impact>
	</event>
	<event>
		<title>MPC Member Tenreyro Speaks</title>
		<currency>GBP</currency>
		<date>24-02-2023</date>
		<time>11:30am</time>
		<forecast></forecast>
		<previous></previous>
		<impact>Low</impact>
	</event>
	<event>
		<title>G20 Meetings</title>
		<currency>All</currency>
		<date>25-02-2023</date>
		<time>Day 4</time>
		<forecast></forecast>
		<previous></previous>
		<impact>Medium</impact>
	</event>
	<event>
		<title>Retail Sales q/q</title>
		<currency>NZD</currency>
		<date>26-02-2023</date>
		<time>4:45pm</time>
		<forecast></forecast>
		<previous>0.4%</previous>
		<impact>Medium</impact>
	</event>
	<event>
		<title>Core Retail Sales q/q</title>
		<currency>NZD</currency>
		<date>26-02-2023</date>
		<time>4:45pm</time>
		<forecast></forecast>
		<previous>0.4%</previous>
		<impact>Low</impact>
	</event>
	<event>
		<title>Company Operating Profits q/q</title>
		<currency>AUD</currency>
		<date>26-02-2023</date>
		<time>7:30pm</time>
		<forecast></forecast>
		<previous>-12.4%</previous>
		<impact>Low</impact>
	</event>
	<event>
		<title>German Import Prices m/m</title>
		<currency>EUR</currency>
		<date>27-02-2023</date>
		<time>27th-2nd</time>
		<forecast></forecast>
		<previous>-1.6%</previous>
		<impact>Low</impact>
	</event>
	<event>
		<title>M3 Money Supply y/y</title>
		<currency>EUR</currency>
		<date>27-02-2023</date>
		<time>4:00am</time>
		<forecast></forecast>
		<previous>4.1%</previous>
		<impact>Low</impact>
	</event>
	<event>
		<title>Private Loans y/y</title>
		<currency>EUR</currency>
		<date>27-02-2023</date>
		<time>4:00am</time>
		<forecast></forecast>
		<previous>3.8%</previous>
		<impact>Low</impact>
	</event>
	<event>
		<title>Current Account</title>
		<currency>CAD</currency>
		<date>27-02-2023</date>
		<time>8:30am</time>
		<forecast></forecast>
		<previous>-11.1B</previous>
		<impact>Low</impact>
	</event>
	<event>
		<title>Core Durable Goods Orders m/m</title>
		<currency>USD</currency>
		<date>27-02-2023</date>
		<time>8:30am</time>
		<forecast></forecast>
		<previous>-0.2%</previous>
		<impact>Medium</impact>
	</event>
	<event>
		<title>Durable Goods Orders m/m</title>
		<currency>USD</currency>
		<date>27-02-2023</date>
		<time>8:30am</time>
		<forecast></forecast>
		<previous>5.6%</previous>
		<impact>Medium</impact>
	</event>
	<event>
		<title>Pending Home Sales m/m</title>
		<currency>USD</currency>
		<date>27-02-2023</date>
		<time>10:00am</time>
		<forecast></forecast>
		<previous>2.5%</previous>
		<impact>Medium</impact>
	</event>
	<event>
		<title>Prelim Industrial Production m/m</title>
		<currency>JPY</currency>
		<date>27-02-2023</date>
		<time>6:50pm</time>
		<forecast></forecast>
		<previous>0.3%</previous>
		<impact>Low</impact>
	</event>
	<event>
		<title>Retail Sales y/y</title>
		<currency>JPY</currency>
		<date>27-02-2023</date>
		<time>6:50pm</time>
		<forecast></forecast>
		<previous>3.8%</previous>
		<impact>Low</impact>
	</event>
	<event>
		<title>ANZ Business Confidence</title>
		<currency>NZD</currency>
		<date>27-02-2023</date>
		<time>7:00pm</time>
		<forecast></forecast>
		<previous>-52.0</previous>
		<impact>Low</impact>
	</event>
	<event>
		<title>Current Account</title>
		<currency>AUD</currency>
		<date>27-02-2023</date>
		<time>7:30pm</time>
		<forecast></forecast>
		<previous>-2.3B</previous>
		<impact>Low</impact>
	</event>
	<event>
		<title>Private Sector Credit m/m</title>
		<currency>AUD</currency>
		<date>27-02-2023</date>
		<time>7:30pm</time>
		<forecast></forecast>
		<previous>0.3%</previous>
		<impact>Low</impact>
	</event>
	<event>
		<title>Retail Sales m/m</title>
		<currency>AUD</currency>
		<date>27-02-2023</date>
		<time>7:30pm</time>
		<forecast></forecast>
		<previous>-3.9%</previous>
		<impact>Low</impact>
	</event>
	<event>
		<title>BOJ Core CPI y/y</title>
		<currency>JPY</currency>
		<date>28-02-2023</date>
		<time>12:00am</time>
		<forecast></forecast>
		<previous>3.1%</previous>
		<impact>Low</impact>
	</event>
	<event>
		<title>Housing Starts y/y</title>
		<currency>JPY</currency>
		<date>28-02-2023</date>
		<time>12:00am</time>
		<forecast></forecast>
		<previous>-1.7%</previous>
		<impact>Low</impact>
	</event>
	<event>
		<title>German Retail Sales m/m</title>
		<currency>EUR</currency>
		<date>28-02-2023</date>
		<time>28th-2nd</time>
		<forecast></forecast>
		<previous></previous>
		<impact>Low</impact>
	</event>
	<event>
		<title>Nationwide HPI m/m</title>
		<currency>GBP</currency>
		<date>28-02-2023</date>
		<time>28th-2nd</time>
		<forecast></forecast>
		<previous></previous>
		<impact>Low</impact>
	</event>
	<event>
		<title>French Consumer Spending m/m</title>
		<currency>EUR</currency>
		<date>28-02-2023</date>
		<time>2:45am</time>
		<forecast></forecast>
		<previous>-1.3%</previous>
		<impact>Low</impact>
	</event>
	<event>
		<title>French Prelim CPI m/m</title>
		<currency>EUR</currency>
		<date>28-02-2023</date>
		<time>2:45am</time>
		<forecast></forecast>
		<previous>0.4%</previous>
		<impact>Low</impact>
	</event>
	<event>
		<title>French Prelim GDP q/q</title>
		<currency>EUR</currency>
		<date>28-02-2023</date>
		<time>2:45am</time>
		<forecast></forecast>
		<previous>0.1%</previous>
		<impact>Low</impact>
	</event>
	<event>
		<title>GDP q/q</title>
		<currency>CHF</currency>
		<date>28-02-2023</date>
		<time>3:00am</time>
		<forecast></forecast>
		<previous>0.2%</previous>
		<impact>Low</impact>
	</event>
	<event>
		<title>KOF Economic Barometer</title>
		<currency>CHF</currency>
		<date>28-02-2023</date>
		<time>3:00am</time>
		<forecast></forecast>
		<previous>97.2</previous>
		<impact>Low</impact>
	</event>
	<event>
		<title>Spanish Flash CPI y/y</title>
		<currency>EUR</currency>
		<date>28-02-2023</date>
		<time>3:00am</time>
		<forecast></forecast>
		<previous>5.9%</previous>
		<impact>Low</impact>
	</event>
	<event>
		<title>GDP m/m</title>
		<currency>CAD</currency>
		<date>28-02-2023</date>
		<time>8:30am</time>
		<forecast></forecast>
		<previous>0.1%</previous>
		<impact>High</impact>
	</event>
	<event>
		<title>Goods Trade Balance</title>
		<currency>USD</currency>
		<date>28-02-2023</date>
		<time>8:30am</time>
		<forecast></forecast>
		<previous>-90.3B</previous>
		<impact>Low</impact>
	</event>
	<event>
		<title>Prelim Wholesale Inventories m/m</title>
		<currency>USD</currency>
		<date>28-02-2023</date>
		<time>8:30am</time>
		<forecast></forecast>
		<previous>0.1%</previous>
		<impact>Low</impact>
	</event>
	<event>
		<title>HPI m/m</title>
		<currency>USD</currency>
		<date>28-02-2023</date>
		<time>9:00am</time>
		<forecast></forecast>
		<previous>-0.1%</previous>
		<impact>Low</impact>
	</event>
	<event>
		<title>S&amp;P/CS Composite-20 HPI y/y</title>
		<currency>USD</currency>
		<date>28-02-2023</date>
		<time>9:00am</time>
		<forecast></forecast>
		<previous>6.8%</previous>
		<impact>Low</impact>
	</event>
	<event>
		<title>Chicago PMI</title>
		<currency>USD</currency>
		<date>28-02-2023</date>
		<time>9:45am</time>
		<forecast></forecast>
		<previous>44.3</previous>
		<impact>Low</impact>
	</event>
	<event>
		<title>CB Consumer Confidence</title>
		<currency>USD</currency>
		<date>28-02-2023</date>
		<time>10:00am</time>
		<forecast></forecast>
		<previous>107.1</previous>
		<impact>High</impact>
	</event>
	<event>
		<title>Richmond Manufacturing Index</title>
		<currency>USD</currency>
		<date>28-02-2023</date>
		<time>10:00am</time>
		<forecast></forecast>
		<previous>-11</previous>
		<impact>Medium</impact>
	</event>
	<event>
		<title>Building Consents m/m</title>
		<currency>NZD</currency>
		<date>28-02-2023</date>
		<time>4:45pm</time>
		<forecast></forecast>
		<previous>-7.2%</previous>
		<impact>Low</impact>
	</event>
	<event>
		<title>BRC Shop Price Index y/y</title>
		<currency>GBP</currency>
		<date>28-02-2023</date>
		<time>7:01pm</time>
		<forecast></forecast>
		<previous>8.0%</previous>
		<impact>Low</impact>
	</event>
	<event>
		<title>CPI y/y</title>
		<currency>AUD</currency>
		<date>28-02-2023</date>
		<time>7:30pm</time>
		<forecast></forecast>
		<previous>8.4%</previous>
		<impact>High</impact>
	</event>
	<event>
		<title>GDP q/q</title>
		<currency>AUD</currency>
		<date>28-02-2023</date>
		<time>7:30pm</time>
		<forecast></forecast>
		<previous>0.6%</previous>
		<impact>Medium</impact>
	</event>
	<event>
		<title>Final Manufacturing PMI</title>
		<currency>JPY</currency>
		<date>28-02-2023</date>
		<time>7:30pm</time>
		<forecast></forecast>
		<previous>47.4</previous>
		<impact>Low</impact>
	</event>
	<event>
		<title>Manufacturing PMI</title>
		<currency>CNY</currency>
		<date>28-02-2023</date>
		<time>8:30pm</time>
		<forecast></forecast>
		<previous>50.1</previous>
		<impact>Low</impact>
	</event>
	<event>
		<title>Non-Manufacturing PMI</title>
		<currency>CNY</currency>
		<date>28-02-2023</date>
		<time>8:30pm</time>
		<forecast></forecast>
		<previous>54.4</previous>
		<impact>Low</impact>
	</event>
	<event>
		<title>Caixin Manufacturing PMI</title>
		<currency>CNY</currency>
		<date>28-02-2023</date>
		<time>8:45pm</time>
		<forecast></forecast>
		<previous>49.2</previous>
		<impact>Low</impact>
	</event>
</monthlyevents>
